[
  {
    "epoch": 1,
    "train": {
      "loss": 5.100881814956665,
      "reg_loss": 0.0009024553000926971,
      "gate_score": 0.49252944625914097,
      "mass": 0.435546875,
      "stiffness": 0.525390625,
      "material": 0.359375
    },
    "val": {
      "loss": 5.053275248583625,
      "reg_loss": 0.0004029414233039407,
      "gate_score": 0.4924823063261369,
      "mass": 0.45588235294117646,
      "stiffness": 0.5294117647058824,
      "material": 0.35294117647058826
    },
    "avg_val_acc": 0.44607843137254904
  },
  {
    "epoch": 2,
    "train": {
      "loss": 4.608851253986359,
      "reg_loss": 0.006821058690547943,
      "gate_score": 0.5422900654375553,
      "mass": 0.603515625,
      "stiffness": 0.556640625,
      "material": 0.505859375
    },
    "val": {
      "loss": 4.363039661856258,
      "reg_loss": 0.013098885031307446,
      "gate_score": 0.5781292775098015,
      "mass": 1.0,
      "stiffness": 0.7941176470588235,
      "material": 0.5441176470588235
    },
    "avg_val_acc": 0.7794117647058822
  },
  {
    "epoch": 3,
    "train": {
      "loss": 3.7312707155942917,
      "reg_loss": 0.051603011786937714,
      "gate_score": 0.6492274850606918,
      "mass": 0.93359375,
      "stiffness": 0.84765625,
      "material": 0.705078125
    },
    "val": {
      "loss": 3.1096219175002155,
      "reg_loss": 0.06818267878364115,
      "gate_score": 0.6782128495328567,
      "mass": 1.0,
      "stiffness": 1.0,
      "material": 0.8088235294117647
    },
    "avg_val_acc": 0.9362745098039215
  },
  {
    "epoch": 4,
    "train": {
      "loss": 2.7075193971395493,
      "reg_loss": 0.08257520943880081,
      "gate_score": 0.6894712559878826,
      "mass": 0.990234375,
      "stiffness": 0.95703125,
      "material": 0.822265625
    },
    "val": {
      "loss": 2.3109696051653694,
      "reg_loss": 0.10057853249942555,
      "gate_score": 0.71461701743743,
      "mass": 1.0,
      "stiffness": 1.0,
      "material": 0.9558823529411765
    },
    "avg_val_acc": 0.9852941176470589
  },
  {
    "epoch": 5,
    "train": {
      "loss": 2.110399544239044,
      "reg_loss": 0.1479087918996811,
      "gate_score": 0.7543539367616177,
      "mass": 0.994140625,
      "stiffness": 0.990234375,
      "material": 0.9296875
    },
    "val": {
      "loss": 1.8113590829512651,
      "reg_loss": 0.21864623883191278,
      "gate_score": 0.8155278458314783,
      "mass": 1.0,
      "stiffness": 1.0,
      "material": 0.8970588235294118
    },
    "avg_val_acc": 0.9656862745098039
  },
  {
    "epoch": 6,
    "train": {
      "loss": 1.6272775679826736,
      "reg_loss": 0.30060321278870106,
      "gate_score": 0.8602685742080212,
      "mass": 0.998046875,
      "stiffness": 1.0,
      "material": 0.974609375
    },
    "val": {
      "loss": 1.3956237750894882,
      "reg_loss": 0.3897938377716962,
      "gate_score": 0.9091751540408415,
      "mass": 1.0,
      "stiffness": 1.0,
      "material": 1.0
    },
    "avg_val_acc": 1.0
  },
  {
    "epoch": 7,
    "train": {
      "loss": 1.2803503796458244,
      "reg_loss": 0.3100845944136381,
      "gate_score": 0.8666194081306458,
      "mass": 1.0,
      "stiffness": 1.0,
      "material": 0.986328125
    },
    "val": {
      "loss": 1.0738232065649593,
      "reg_loss": 0.20114914284032934,
      "gate_score": 0.8034269178614897,
      "mass": 1.0,
      "stiffness": 1.0,
      "material": 1.0
    },
    "avg_val_acc": 1.0
  },
  {
    "epoch": 8,
    "train": {
      "loss": 0.9737128987908363,
      "reg_loss": 0.12313249334692955,
      "gate_score": 0.719295397400856,
      "mass": 0.998046875,
      "stiffness": 0.998046875,
      "material": 0.98828125
    },
    "val": {
      "loss": 0.832753928268657,
      "reg_loss": 0.024356533499325022,
      "gate_score": 0.5666870509876925,
      "mass": 1.0,
      "stiffness": 1.0,
      "material": 1.0
    },
    "avg_val_acc": 1.0
  },
  {
    "epoch": 9,
    "train": {
      "loss": 0.7266119979321957,
      "reg_loss": 0.025841563940048218,
      "gate_score": 0.5615393742918968,
      "mass": 1.0,
      "stiffness": 1.0,
      "material": 0.994140625
    },
    "val": {
      "loss": 0.6443929321625653,
      "reg_loss": 0.01395572634304271,
      "gate_score": 0.530212311183705,
      "mass": 1.0,
      "stiffness": 1.0,
      "material": 1.0
    },
    "avg_val_acc": 1.0
  },
  {
    "epoch": 10,
    "train": {
      "loss": 0.586943719536066,
      "reg_loss": 0.01659531146287918,
      "gate_score": 0.5313777253031731,
      "mass": 0.998046875,
      "stiffness": 0.998046875,
      "material": 0.984375
    },
    "val": {
      "loss": 0.5215960811166203,
      "reg_loss": 0.02470165491104126,
      "gate_score": 0.5901893096811631,
      "mass": 1.0,
      "stiffness": 1.0,
      "material": 1.0
    },
    "avg_val_acc": 1.0
  },
  {
    "epoch": 11,
    "train": {
      "loss": 0.5184731241315603,
      "reg_loss": 0.030690249055624008,
      "gate_score": 0.5924144051969051,
      "mass": 0.998046875,
      "stiffness": 1.0,
      "material": 0.978515625
    },
    "val": {
      "loss": 0.4339841288678786,
      "reg_loss": 0.024897456169128418,
      "gate_score": 0.5737057152916404,
      "mass": 1.0,
      "stiffness": 1.0,
      "material": 1.0
    },
    "avg_val_acc": 1.0
  },
  {
    "epoch": 12,
    "train": {
      "loss": 0.4083772376179695,
      "reg_loss": 0.018453828990459442,
      "gate_score": 0.4976936783641577,
      "mass": 1.0,
      "stiffness": 1.0,
      "material": 0.986328125
    },
    "val": {
      "loss": 0.35770755305009727,
      "reg_loss": 0.009944992906907025,
      "gate_score": 0.5045711292940027,
      "mass": 1.0,
      "stiffness": 1.0,
      "material": 1.0
    },
    "avg_val_acc": 1.0
  },
  {
    "epoch": 13,
    "train": {
      "loss": 0.34794880263507366,
      "reg_loss": 0.021054916083812714,
      "gate_score": 0.5667577031999826,
      "mass": 1.0,
      "stiffness": 1.0,
      "material": 0.986328125
    },
    "val": {
      "loss": 0.3088267042356379,
      "reg_loss": 0.011601668946883258,
      "gate_score": 0.5460539915982414,
      "mass": 1.0,
      "stiffness": 1.0,
      "material": 1.0
    },
    "avg_val_acc": 1.0
  },
  {
    "epoch": 14,
    "train": {
      "loss": 0.30699222162365913,
      "reg_loss": 0.010899282991886139,
      "gate_score": 0.509883688762784,
      "mass": 1.0,
      "stiffness": 1.0,
      "material": 0.98828125
    },
    "val": {
      "loss": 0.264647876515108,
      "reg_loss": 0.008070847567389993,
      "gate_score": 0.4941602209035088,
      "mass": 1.0,
      "stiffness": 1.0,
      "material": 1.0
    },
    "avg_val_acc": 1.0
  },
  {
    "epoch": 15,
    "train": {
      "loss": 0.324622156098485,
      "reg_loss": 0.010132048279047012,
      "gate_score": 0.5236441101878881,
      "mass": 1.0,
      "stiffness": 1.0,
      "material": 0.978515625
    },
    "val": {
      "loss": 0.2444599638966953,
      "reg_loss": 0.008042458225699031,
      "gate_score": 0.5369297195883358,
      "mass": 1.0,
      "stiffness": 1.0,
      "material": 1.0
    },
    "avg_val_acc": 1.0
  },
  {
    "epoch": 16,
    "train": {
      "loss": 0.2515454227104783,
      "reg_loss": 0.006957929581403732,
      "gate_score": 0.5065255165100098,
      "mass": 1.0,
      "stiffness": 1.0,
      "material": 0.990234375
    },
    "val": {
      "loss": 0.20982247240403118,
      "reg_loss": 0.0038841647260329302,
      "gate_score": 0.49435120470383587,
      "mass": 1.0,
      "stiffness": 1.0,
      "material": 1.0
    },
    "avg_val_acc": 1.0
  },
  {
    "epoch": 17,
    "train": {
      "loss": 0.28053778037428856,
      "reg_loss": 0.01438865065574646,
      "gate_score": 0.5580303221940994,
      "mass": 0.998046875,
      "stiffness": 0.998046875,
      "material": 0.98828125
    },
    "val": {
      "loss": 0.19433413884219,
      "reg_loss": 0.006070158060859232,
      "gate_score": 0.5180956125259399,
      "mass": 1.0,
      "stiffness": 1.0,
      "material": 1.0
    },
    "avg_val_acc": 1.0
  },
  {
    "epoch": 18,
    "train": {
      "loss": 0.2505359994247556,
      "reg_loss": 0.007795494049787521,
      "gate_score": 0.48695263266563416,
      "mass": 1.0,
      "stiffness": 1.0,
      "material": 0.978515625
    },
    "val": {
      "loss": 0.17352283176253824,
      "reg_loss": 0.00543203774620505,
      "gate_score": 0.5150142452296089,
      "mass": 1.0,
      "stiffness": 1.0,
      "material": 1.0
    },
    "avg_val_acc": 1.0
  },
  {
    "epoch": 19,
    "train": {
      "loss": 0.27055203448981047,
      "reg_loss": 0.006563808768987656,
      "gate_score": 0.5258152242749929,
      "mass": 0.998046875,
      "stiffness": 0.998046875,
      "material": 0.978515625
    },
    "val": {
      "loss": 0.17274768036954544,
      "reg_loss": 0.0028563211945926443,
      "gate_score": 0.5015452188604018,
      "mass": 1.0,
      "stiffness": 1.0,
      "material": 1.0
    },
    "avg_val_acc": 1.0
  },
  {
    "epoch": 20,
    "train": {
      "loss": 0.19858575146645308,
      "reg_loss": 0.0043357014656066895,
      "gate_score": 0.5137623436748981,
      "mass": 1.0,
      "stiffness": 1.0,
      "material": 0.994140625
    },
    "val": {
      "loss": 0.15657668955185833,
      "reg_loss": 0.0024119931108811323,
      "gate_score": 0.4988028126604417,
      "mass": 1.0,
      "stiffness": 1.0,
      "material": 1.0
    },
    "avg_val_acc": 1.0
  },
  {
    "epoch": 21,
    "train": {
      "loss": 0.20299801882356405,
      "reg_loss": 0.004189383238554001,
      "gate_score": 0.5164679922163486,
      "mass": 1.0,
      "stiffness": 1.0,
      "material": 0.986328125
    },
    "val": {
      "loss": 0.1433847073246451,
      "reg_loss": 0.0033762525109683767,
      "gate_score": 0.5059883278958938,
      "mass": 1.0,
      "stiffness": 1.0,
      "material": 1.0
    },
    "avg_val_acc": 1.0
  },
  {
    "epoch": 22,
    "train": {
      "loss": 0.17529546562582254,
      "reg_loss": 0.0037015751004219055,
      "gate_score": 0.5088420212268829,
      "mass": 1.0,
      "stiffness": 1.0,
      "material": 0.98828125
    },
    "val": {
      "loss": 0.13868475486250484,
      "reg_loss": 0.0021098150926477767,
      "gate_score": 0.5101113740135642,
      "mass": 1.0,
      "stiffness": 1.0,
      "material": 1.0
    },
    "avg_val_acc": 1.0
  },
  {
    "epoch": 23,
    "train": {
      "loss": 0.160098847001791,
      "reg_loss": 0.0020716749131679535,
      "gate_score": 0.5016824826598167,
      "mass": 1.0,
      "stiffness": 1.0,
      "material": 0.994140625
    },
    "val": {
      "loss": 0.1262873130686143,
      "reg_loss": 0.0011552712496589212,
      "gate_score": 0.503709894769332,
      "mass": 1.0,
      "stiffness": 1.0,
      "material": 1.0
    },
    "avg_val_acc": 1.0
  },
  {
    "epoch": 24,
    "train": {
      "loss": 0.17134867561981082,
      "reg_loss": 0.0014356188476085663,
      "gate_score": 0.5005994644016027,
      "mass": 1.0,
      "stiffness": 1.0,
      "material": 0.986328125
    },
    "val": {
      "loss": 0.12420808918335859,
      "reg_loss": 0.0013840689378626207,
      "gate_score": 0.4909057792495279,
      "mass": 1.0,
      "stiffness": 1.0,
      "material": 1.0
    },
    "avg_val_acc": 1.0
  },
  {
    "epoch": 25,
    "train": {
      "loss": 0.16566690197214484,
      "reg_loss": 0.0034524649381637573,
      "gate_score": 0.5218132026493549,
      "mass": 1.0,
      "stiffness": 1.0,
      "material": 0.994140625
    },
    "val": {
      "loss": 0.11458916436223422,
      "reg_loss": 0.0030015987508437213,
      "gate_score": 0.52654889050652,
      "mass": 1.0,
      "stiffness": 1.0,
      "material": 1.0
    },
    "avg_val_acc": 1.0
  },
  {
    "epoch": 26,
    "train": {
      "loss": 0.15550042502582073,
      "reg_loss": 0.002555977553129196,
      "gate_score": 0.4974338077008724,
      "mass": 1.0,
      "stiffness": 1.0,
      "material": 0.994140625
    },
    "val": {
      "loss": 0.11865981010829701,
      "reg_loss": 0.0013326196109547334,
      "gate_score": 0.5023466979756075,
      "mass": 1.0,
      "stiffness": 1.0,
      "material": 1.0
    },
    "avg_val_acc": 1.0
  },
  {
    "epoch": 27,
    "train": {
      "loss": 0.16044158954173326,
      "reg_loss": 0.0020065754652023315,
      "gate_score": 0.5077778212726116,
      "mass": 1.0,
      "stiffness": 1.0,
      "material": 0.9921875
    },
    "val": {
      "loss": 0.11167226118199966,
      "reg_loss": 0.0011357489754171932,
      "gate_score": 0.491703566382913,
      "mass": 1.0,
      "stiffness": 1.0,
      "material": 1.0
    },
    "avg_val_acc": 1.0
  },
  {
    "epoch": 28,
    "train": {
      "loss": 0.18251765938475728,
      "reg_loss": 0.0012115202844142914,
      "gate_score": 0.49674114771187305,
      "mass": 1.0,
      "stiffness": 1.0,
      "material": 0.990234375
    },
    "val": {
      "loss": 0.1096411373685388,
      "reg_loss": 0.0008296615937176873,
      "gate_score": 0.5033980923540452,
      "mass": 1.0,
      "stiffness": 1.0,
      "material": 1.0
    },
    "avg_val_acc": 1.0
  },
  {
    "epoch": 29,
    "train": {
      "loss": 0.15572617994621396,
      "reg_loss": 0.001394461840391159,
      "gate_score": 0.5113100484013557,
      "mass": 0.99609375,
      "stiffness": 1.0,
      "material": 0.99609375
    },
    "val": {
      "loss": 0.11283576137879316,
      "reg_loss": 0.0012635238030377556,
      "gate_score": 0.5087556558496812,
      "mass": 1.0,
      "stiffness": 1.0,
      "material": 1.0
    },
    "avg_val_acc": 1.0
  },
  {
    "epoch": 30,
    "train": {
      "loss": 0.1636595674790442,
      "reg_loss": 0.002119172364473343,
      "gate_score": 0.5014202855527401,
      "mass": 1.0,
      "stiffness": 1.0,
      "material": 0.98828125
    },
    "val": {
      "loss": 0.11458963506362017,
      "reg_loss": 0.002939013873829561,
      "gate_score": 0.47105109691619873,
      "mass": 1.0,
      "stiffness": 1.0,
      "material": 1.0
    },
    "avg_val_acc": 1.0
  },
  {
    "epoch": 31,
    "train": {
      "loss": 0.13490126049146056,
      "reg_loss": 0.0018171034753322601,
      "gate_score": 0.49177449010312557,
      "mass": 1.0,
      "stiffness": 1.0,
      "material": 0.990234375
    },
    "val": {
      "loss": 0.1059313583023408,
      "reg_loss": 0.0009173084707821117,
      "gate_score": 0.5097490233533523,
      "mass": 1.0,
      "stiffness": 1.0,
      "material": 1.0
    },
    "avg_val_acc": 1.0
  },
  {
    "epoch": 32,
    "train": {
      "loss": 0.1621554596349597,
      "reg_loss": 0.0016732700169086456,
      "gate_score": 0.5191061086952686,
      "mass": 0.998046875,
      "stiffness": 0.998046875,
      "material": 0.990234375
    },
    "val": {
      "loss": 0.1035468175130732,
      "reg_loss": 0.002357335651622099,
      "gate_score": 0.5293439205955056,
      "mass": 1.0,
      "stiffness": 1.0,
      "material": 1.0
    },
    "avg_val_acc": 1.0
  },
  {
    "epoch": 33,
    "train": {
      "loss": 0.1224908703006804,
      "reg_loss": 0.0019025616347789764,
      "gate_score": 0.5148956626653671,
      "mass": 1.0,
      "stiffness": 1.0,
      "material": 0.998046875
    },
    "val": {
      "loss": 0.09865881239666659,
      "reg_loss": 0.0014474602306590362,
      "gate_score": 0.48191124200820923,
      "mass": 1.0,
      "stiffness": 1.0,
      "material": 1.0
    },
    "avg_val_acc": 1.0
  },
  {
    "epoch": 34,
    "train": {
      "loss": 0.1264341762289405,
      "reg_loss": 0.0010152384638786316,
      "gate_score": 0.49406821094453335,
      "mass": 1.0,
      "stiffness": 1.0,
      "material": 0.998046875
    },
    "val": {
      "loss": 0.09836484930094551,
      "reg_loss": 0.0006645742584677303,
      "gate_score": 0.4946923571474412,
      "mass": 1.0,
      "stiffness": 1.0,
      "material": 1.0
    },
    "avg_val_acc": 1.0
  },
  {
    "epoch": 35,
    "train": {
      "loss": 0.13950356096029282,
      "reg_loss": 0.0007468611001968384,
      "gate_score": 0.5002025291323662,
      "mass": 0.998046875,
      "stiffness": 0.998046875,
      "material": 0.994140625
    },
    "val": {
      "loss": 0.09911868502111996,
      "reg_loss": 0.0007351005778593175,
      "gate_score": 0.4913033176870907,
      "mass": 1.0,
      "stiffness": 1.0,
      "material": 1.0
    },
    "avg_val_acc": 1.0
  },
  {
    "epoch": 36,
    "train": {
      "loss": 0.1320992736145854,
      "reg_loss": 0.0007233172655105591,
      "gate_score": 0.4996256735175848,
      "mass": 1.0,
      "stiffness": 1.0,
      "material": 0.99609375
    },
    "val": {
      "loss": 0.0931716245763442,
      "reg_loss": 0.0006183455972110524,
      "gate_score": 0.4958914974156548,
      "mass": 1.0,
      "stiffness": 1.0,
      "material": 1.0
    },
    "avg_val_acc": 1.0
  },
  {
    "epoch": 37,
    "train": {
      "loss": 0.13055584114044905,
      "reg_loss": 0.0007199905812740326,
      "gate_score": 0.4993975665420294,
      "mass": 1.0,
      "stiffness": 1.0,
      "material": 0.994140625
    },
    "val": {
      "loss": 0.09334428170148064,
      "reg_loss": 0.0008371121743146111,
      "gate_score": 0.489817491349052,
      "mass": 1.0,
      "stiffness": 1.0,
      "material": 1.0
    },
    "avg_val_acc": 1.0
  },
  {
    "epoch": 38,
    "train": {
      "loss": 0.13543544616550207,
      "reg_loss": 0.0007559992372989655,
      "gate_score": 0.4995927643030882,
      "mass": 0.998046875,
      "stiffness": 0.998046875,
      "material": 0.99609375
    },
    "val": {
      "loss": 0.09135115058983073,
      "reg_loss": 0.0005536780637853286,
      "gate_score": 0.5002296356593862,
      "mass": 1.0,
      "stiffness": 1.0,
      "material": 1.0
    },
    "avg_val_acc": 1.0
  },
  {
    "epoch": 39,
    "train": {
      "loss": 0.12875386117957532,
      "reg_loss": 0.0008961483836174011,
      "gate_score": 0.5099756233394146,
      "mass": 1.0,
      "stiffness": 1.0,
      "material": 0.990234375
    },
    "val": {
      "loss": 0.08936858264838948,
      "reg_loss": 0.0005540006300982307,
      "gate_score": 0.503652036190033,
      "mass": 1.0,
      "stiffness": 1.0,
      "material": 1.0
    },
    "avg_val_acc": 1.0
  },
  {
    "epoch": 40,
    "train": {
      "loss": 0.12890902580693364,
      "reg_loss": 0.0007284767925739288,
      "gate_score": 0.5031379163265228,
      "mass": 1.0,
      "stiffness": 1.0,
      "material": 0.98828125
    },
    "val": {
      "loss": 0.08911069000468534,
      "reg_loss": 0.0005788557669695686,
      "gate_score": 0.49503055916113015,
      "mass": 1.0,
      "stiffness": 1.0,
      "material": 1.0
    },
    "avg_val_acc": 1.0
  },
  {
    "epoch": 41,
    "train": {
      "loss": 0.12388248811475933,
      "reg_loss": 0.0007052607834339142,
      "gate_score": 0.5029415339231491,
      "mass": 1.0,
      "stiffness": 1.0,
      "material": 0.990234375
    },
    "val": {
      "loss": 0.08882547827327952,
      "reg_loss": 0.0004946063546573414,
      "gate_score": 0.4988535852993236,
      "mass": 1.0,
      "stiffness": 1.0,
      "material": 1.0
    },
    "avg_val_acc": 1.0
  },
  {
    "epoch": 42,
    "train": {
      "loss": 0.1796039715409279,
      "reg_loss": 0.0007484667003154755,
      "gate_score": 0.5041497834026814,
      "mass": 0.998046875,
      "stiffness": 0.998046875,
      "material": 0.9921875
    },
    "val": {
      "loss": 0.0872435797663296,
      "reg_loss": 0.0005072670824387495,
      "gate_score": 0.4989534090547001,
      "mass": 1.0,
      "stiffness": 1.0,
      "material": 1.0
    },
    "avg_val_acc": 1.0
  },
  {
    "epoch": 43,
    "train": {
      "loss": 0.11049538804218173,
      "reg_loss": 0.0007658973336219788,
      "gate_score": 0.501851499080658,
      "mass": 1.0,
      "stiffness": 1.0,
      "material": 0.99609375
    },
    "val": {
      "loss": 0.08725747992010678,
      "reg_loss": 0.0005423672059003045,
      "gate_score": 0.4948682294172399,
      "mass": 1.0,
      "stiffness": 1.0,
      "material": 1.0
    },
    "avg_val_acc": 1.0
  },
  {
    "epoch": 44,
    "train": {
      "loss": 0.1382624637335539,
      "reg_loss": 0.0006696134805679321,
      "gate_score": 0.49762983806431293,
      "mass": 1.0,
      "stiffness": 1.0,
      "material": 0.990234375
    },
    "val": {
      "loss": 0.08900218062541064,
      "reg_loss": 0.0005880313761094037,
      "gate_score": 0.49226541729534373,
      "mass": 1.0,
      "stiffness": 1.0,
      "material": 1.0
    },
    "avg_val_acc": 1.0
  },
  {
    "epoch": 45,
    "train": {
      "loss": 0.12783107301220298,
      "reg_loss": 0.0006828606128692627,
      "gate_score": 0.49881274066865444,
      "mass": 1.0,
      "stiffness": 1.0,
      "material": 0.98828125
    },
    "val": {
      "loss": 0.0863436478025773,
      "reg_loss": 0.0005007736823138068,
      "gate_score": 0.4972870980992037,
      "mass": 1.0,
      "stiffness": 1.0,
      "material": 1.0
    },
    "avg_val_acc": 1.0
  },
  {
    "epoch": 46,
    "train": {
      "loss": 0.11781917186453938,
      "reg_loss": 0.0006457008421421051,
      "gate_score": 0.4999923314899206,
      "mass": 1.0,
      "stiffness": 1.0,
      "material": 0.990234375
    },
    "val": {
      "loss": 0.08784987908952377,
      "reg_loss": 0.0005559009664198931,
      "gate_score": 0.4933014512062073,
      "mass": 1.0,
      "stiffness": 1.0,
      "material": 1.0
    },
    "avg_val_acc": 1.0
  },
  {
    "epoch": 47,
    "train": {
      "loss": 0.111472844844684,
      "reg_loss": 0.0006317347288131714,
      "gate_score": 0.4988688491284847,
      "mass": 1.0,
      "stiffness": 1.0,
      "material": 0.99609375
    },
    "val": {
      "loss": 0.0858954866142834,
      "reg_loss": 0.0005344082327450023,
      "gate_score": 0.4943724537596983,
      "mass": 1.0,
      "stiffness": 1.0,
      "material": 1.0
    },
    "avg_val_acc": 1.0
  },
  {
    "epoch": 48,
    "train": {
      "loss": 0.1186733830254525,
      "reg_loss": 0.0006562024354934692,
      "gate_score": 0.49902911670506,
      "mass": 1.0,
      "stiffness": 1.0,
      "material": 0.98828125
    },
    "val": {
      "loss": 0.08485270861317129,
      "reg_loss": 0.000556482988245347,
      "gate_score": 0.4933290481567383,
      "mass": 1.0,
      "stiffness": 1.0,
      "material": 1.0
    },
    "avg_val_acc": 1.0
  },
  {
    "epoch": 49,
    "train": {
      "loss": 0.11509829270653427,
      "reg_loss": 0.000684443861246109,
      "gate_score": 0.49506079591810703,
      "mass": 0.998046875,
      "stiffness": 1.0,
      "material": 0.99609375
    },
    "val": {
      "loss": 0.08482040201916415,
      "reg_loss": 0.0008101498379426844,
      "gate_score": 0.48727674168698926,
      "mass": 1.0,
      "stiffness": 1.0,
      "material": 1.0
    },
    "avg_val_acc": 1.0
  },
  {
    "epoch": 50,
    "train": {
      "loss": 0.13634016341529787,
      "reg_loss": 0.0007170550525188446,
      "gate_score": 0.49284575693309307,
      "mass": 1.0,
      "stiffness": 1.0,
      "material": 0.990234375
    },
    "val": {
      "loss": 0.08558208802167107,
      "reg_loss": 0.0008253244792713839,
      "gate_score": 0.4869746074957006,
      "mass": 1.0,
      "stiffness": 1.0,
      "material": 1.0
    },
    "avg_val_acc": 1.0
  },
  {
    "epoch": 51,
    "train": {
      "loss": 0.1368739523459226,
      "reg_loss": 0.0007062181830406189,
      "gate_score": 0.4940536357462406,
      "mass": 0.998046875,
      "stiffness": 1.0,
      "material": 0.994140625
    },
    "val": {
      "loss": 0.08398926433394938,
      "reg_loss": 0.0006587294971241671,
      "gate_score": 0.4904981220469755,
      "mass": 1.0,
      "stiffness": 1.0,
      "material": 1.0
    },
    "avg_val_acc": 1.0
  },
  {
    "epoch": 52,
    "train": {
      "loss": 0.14806523732841015,
      "reg_loss": 0.0005895271897315979,
      "gate_score": 0.4981474503874779,
      "mass": 0.998046875,
      "stiffness": 0.998046875,
      "material": 0.990234375
    },
    "val": {
      "loss": 0.08360089536975412,
      "reg_loss": 0.0005547614658580107,
      "gate_score": 0.49331845430766835,
      "mass": 1.0,
      "stiffness": 1.0,
      "material": 1.0
    },
    "avg_val_acc": 1.0
  },
  {
    "epoch": 53,
    "train": {
      "loss": 0.10778688825666904,
      "reg_loss": 0.0006618313491344452,
      "gate_score": 0.4974132161587477,
      "mass": 1.0,
      "stiffness": 1.0,
      "material": 1.0
    },
    "val": {
      "loss": 0.08478547369732577,
      "reg_loss": 0.0005784665837007411,
      "gate_score": 0.49201805801952586,
      "mass": 1.0,
      "stiffness": 1.0,
      "material": 1.0
    },
    "avg_val_acc": 1.0
  },
  {
    "epoch": 54,
    "train": {
      "loss": 0.10985564207658172,
      "reg_loss": 0.0006097853183746338,
      "gate_score": 0.4975812714546919,
      "mass": 1.0,
      "stiffness": 1.0,
      "material": 0.99609375
    },
    "val": {
      "loss": 0.08496026957736295,
      "reg_loss": 0.0005765171612010282,
      "gate_score": 0.4917587217162637,
      "mass": 1.0,
      "stiffness": 1.0,
      "material": 1.0
    },
    "avg_val_acc": 1.0
  },
  {
    "epoch": 55,
    "train": {
      "loss": 0.11472027469426394,
      "reg_loss": 0.0006500259041786194,
      "gate_score": 0.49773453548550606,
      "mass": 1.0,
      "stiffness": 1.0,
      "material": 0.99609375
    },
    "val": {
      "loss": 0.08466271267217748,
      "reg_loss": 0.0005781685604768641,
      "gate_score": 0.49169456608155193,
      "mass": 1.0,
      "stiffness": 1.0,
      "material": 1.0
    },
    "avg_val_acc": 1.0
  },
  {
    "epoch": 56,
    "train": {
      "loss": 0.1027008097153157,
      "reg_loss": 0.0006473809480667114,
      "gate_score": 0.4975019805133343,
      "mass": 1.0,
      "stiffness": 1.0,
      "material": 0.998046875
    },
    "val": {
      "loss": 0.08396438377745011,
      "reg_loss": 0.000594938502592199,
      "gate_score": 0.4917043605271508,
      "mass": 1.0,
      "stiffness": 1.0,
      "material": 1.0
    },
    "avg_val_acc": 1.0
  },
  {
    "epoch": 57,
    "train": {
      "loss": 0.12655854038894176,
      "reg_loss": 0.000597883015871048,
      "gate_score": 0.4981675073504448,
      "mass": 1.0,
      "stiffness": 1.0,
      "material": 0.990234375
    },
    "val": {
      "loss": 0.08446225962218117,
      "reg_loss": 0.0005615739261402804,
      "gate_score": 0.49245253380607157,
      "mass": 1.0,
      "stiffness": 1.0,
      "material": 1.0
    },
    "avg_val_acc": 1.0
  },
  {
    "epoch": 58,
    "train": {
      "loss": 0.1262913509272039,
      "reg_loss": 0.0005778484046459198,
      "gate_score": 0.49911046400666237,
      "mass": 1.0,
      "stiffness": 1.0,
      "material": 0.990234375
    },
    "val": {
      "loss": 0.08453582139576182,
      "reg_loss": 0.0005202433642219095,
      "gate_score": 0.4940534146393047,
      "mass": 1.0,
      "stiffness": 1.0,
      "material": 1.0
    },
    "avg_val_acc": 1.0
  },
  {
    "epoch": 59,
    "train": {
      "loss": 0.11284078704193234,
      "reg_loss": 0.0006061121821403503,
      "gate_score": 0.49729575030505657,
      "mass": 1.0,
      "stiffness": 1.0,
      "material": 0.99609375
    },
    "val": {
      "loss": 0.08394816868445452,
      "reg_loss": 0.0005745431956122903,
      "gate_score": 0.4922892591532539,
      "mass": 1.0,
      "stiffness": 1.0,
      "material": 1.0
    },
    "avg_val_acc": 1.0
  },
  {
    "epoch": 60,
    "train": {
      "loss": 0.10030522919259965,
      "reg_loss": 0.0005985386669635773,
      "gate_score": 0.49800457060337067,
      "mass": 1.0,
      "stiffness": 1.0,
      "material": 0.99609375
    },
    "val": {
      "loss": 0.08377091498935924,
      "reg_loss": 0.0005280761157765108,
      "gate_score": 0.49372680572902455,
      "mass": 1.0,
      "stiffness": 1.0,
      "material": 1.0
    },
    "avg_val_acc": 1.0
  }
]